desafio_poo/__init__.py
desafio_poo/desafio_poov1.py
desafio_poo-0.0.1.dist-info/METADATA
desafio_poo-0.0.1.dist-info/WHEEL
desafio_poo-0.0.1.dist-info/top_level.txt
desafio_poo-0.0.1.dist-info/RECORD
