Metadata-Version: 2.1
Name: desafio_poo
Version: 0.0.1
Summary: desafio poo
Home-page: https://github.com/Diego-Alvesds
Author: Diego Alves
Author-email: diegoalvesds@outlook.com
Requires-Python: >=3.8
